instapy/__init__.py
instapy/credentials.py
instapy/dm.py
instapy/login.py
instapytool-0.1.1.dist-info/licenses/LICENSE
instapytool-0.1.1.dist-info/METADATA
instapytool-0.1.1.dist-info/WHEEL
instapytool-0.1.1.dist-info/top_level.txt
instapytool-0.1.1.dist-info/RECORD
