Metadata-Version: 2.4
Name: instapytool
Version: 0.1.1
Summary: Send Instagram DMs using session ID automation with Selenium
Home-page: https://github.com/prajjwalnag/InstaPy
Author: Prajjwal Nag
Author-email: your.email@example.com
License: MIT
Project-URL: Source, https://github.com/prajjwalnag/InstaPy
Project-URL: Bug Tracker, https://github.com/prajjwalnag/InstaPy/issues
Classifier: Programming Language :: Python :: 3
Classifier: License :: OSI Approved :: MIT License
Classifier: Operating System :: OS Independent
Classifier: Topic :: Communications :: Chat
Classifier: Topic :: Software Development :: Libraries :: Python Modules
Requires-Python: >=3.7
License-File: LICENSE
Requires-Dist: selenium>=4.0.0
Requires-Dist: fastapi>=0.78.0
Requires-Dist: pydantic>=1.10.0
Dynamic: author
Dynamic: author-email
Dynamic: classifier
Dynamic: description
Dynamic: description-content-type
Dynamic: home-page
Dynamic: license
Dynamic: license-file
Dynamic: project-url
Dynamic: requires-dist
Dynamic: requires-python
Dynamic: summary
